petal_qc/PetalReceptionTests.py
petal_qc/__init__.py
petal_qc/dashBoard.py
petal_qc/getPetalCoreTestSummary.py
petal_qc/readTemplateTable.py
petal_qc/uploadAllMetrology.py
petal_qc/uploadXrays.py
petal_qc/BTreport/CheckBTtests.py
petal_qc/BTreport/__init__.py
petal_qc/BTreport/bustapeReport.py
petal_qc/metrology/Cluster.py
petal_qc/metrology/DataFile.py
petal_qc/metrology/PetalMetrology.py
petal_qc/metrology/__init__.py
petal_qc/metrology/all2csv.py
petal_qc/metrology/analyze_locking_points.py
petal_qc/metrology/cold_noise.py
petal_qc/metrology/compare_Cores.py
petal_qc/metrology/comparisonTable.py
petal_qc/metrology/convert_mitutoyo.py
petal_qc/metrology/convert_smartscope.py
petal_qc/metrology/coreMetrology.py
petal_qc/metrology/data2csv.py
petal_qc/metrology/do_Metrology.py
petal_qc/metrology/flatness4nigel.py
petal_qc/metrology/gtkutils.py
petal_qc/metrology/petal_flatness.py
petal_qc/metrology/readAVSdata.py
petal_qc/metrology/show_data_file.py
petal_qc/metrology/testSummary.py
petal_qc/metrology/test_paralelism.py
petal_qc/metrology/uploadPetalInformation.py
petal_qc/test/analyzeMetrologyTable.py
petal_qc/test/checkAVStests.py
petal_qc/test/checkCoreShipments.py
petal_qc/test/checkPipeShipments.py
petal_qc/test/compare_golden.py
petal_qc/test/createMetrologyFile.py
petal_qc/test/createMetrologyTable.py
petal_qc/test/desyModuleBow.py
petal_qc/test/findRawData.py
petal_qc/test/getAVSjson.py
petal_qc/test/getAVStests.py
petal_qc/test/listPetalCoreComponents.py
petal_qc/test/prepareDESYfiles.py
petal_qc/test/reportFromJSon.py
petal_qc/test/testMitutoyo.py
petal_qc/test/test_Graphana.py
petal_qc/test/test_coreThermal.py
petal_qc/test/thermalReportFromJSon.py
petal_qc/thermal/CSVImage.py
petal_qc/thermal/DESYdata.py
petal_qc/thermal/DebugPlot.py
petal_qc/thermal/IRBFile.py
petal_qc/thermal/IRCore.py
petal_qc/thermal/IRDataGetter.py
petal_qc/thermal/IRPetal.py
petal_qc/thermal/IRPetalParam.py
petal_qc/thermal/PetalColorMaps.py
petal_qc/thermal/Petal_IR_Analysis.py
petal_qc-0.0.26.dist-info/METADATA
petal_qc-0.0.26.dist-info/WHEEL
petal_qc-0.0.26.dist-info/entry_points.txt
petal_qc-0.0.26.dist-info/top_level.txt
petal_qc-0.0.26.dist-info/RECORD
