Metadata-Version: 2.4
Name: petal_qc
Version: 0.0.26
Summary: A collection of scripts for Petal CORE QC.
Author-email: Carlos Lacasta <carlos.lacasta@cern.ch>
Project-URL: Homepage, https://gitlab.cern.ch/atlas-itk/sw/db/itk-pdb-gtk-gui-utils
Project-URL: Bug Tracker, https://gitlab.cern.ch/atlas-itk/sw/db/itk-pdb-gtk-gui-utils/-/issues
Classifier: Programming Language :: Python :: 3
Classifier: Operating System :: OS Independent
Requires-Python: >=3.7
Requires-Dist: itkdb
Requires-Dist: itkdb_gtk>=0.10.10
Requires-Dist: numpy
Requires-Dist: matplotlib
Requires-Dist: lmfit
Requires-Dist: openpyxl
Requires-Dist: pandas
Requires-Dist: python_dateutil
Requires-Dist: python_docx
Requires-Dist: scipy
